<annotation>
	<folder></folder>
	<filename>006_jpg.rf.36b9079de6f048e81edf9996e80c70f4.jpg</filename>
	<path>006_jpg.rf.36b9079de6f048e81edf9996e80c70f4.jpg</path>
	<source>
		<database>roboflow.ai</database>
	</source>
	<size>
		<width>640</width>
		<height>640</height>
		<depth>3</depth>
	</size>
	<segmented>0</segmented>
	<object>
		<name>datamatrix</name>
		<pose>Unspecified</pose>
		<truncated>0</truncated>
		<difficult>0</difficult>
		<occluded>0</occluded>
		<bndbox>
			<xmin>258</xmin>
			<xmax>309</xmax>
			<ymin>80</ymin>
			<ymax>113</ymax>
		</bndbox>
	</object>
	<object>
		<name>datamatrix</name>
		<pose>Unspecified</pose>
		<truncated>0</truncated>
		<difficult>0</difficult>
		<occluded>0</occluded>
		<bndbox>
			<xmin>268</xmin>
			<xmax>328</xmax>
			<ymin>237</ymin>
			<ymax>276</ymax>
		</bndbox>
	</object>
	<object>
		<name>datamatrix</name>
		<pose>Unspecified</pose>
		<truncated>0</truncated>
		<difficult>0</difficult>
		<occluded>0</occluded>
		<bndbox>
			<xmin>173</xmin>
			<xmax>232</xmax>
			<ymin>311</ymin>
			<ymax>348</ymax>
		</bndbox>
	</object>
</annotation>
