<annotation>
	<folder></folder>
	<filename>2964565796_jpg.rf.568fed337c8546c6e61623661c58d7d8.jpg</filename>
	<path>2964565796_jpg.rf.568fed337c8546c6e61623661c58d7d8.jpg</path>
	<source>
		<database>roboflow.ai</database>
	</source>
	<size>
		<width>640</width>
		<height>640</height>
		<depth>3</depth>
	</size>
	<segmented>0</segmented>
	<object>
		<name>qrcode</name>
		<pose>Unspecified</pose>
		<truncated>0</truncated>
		<difficult>0</difficult>
		<occluded>0</occluded>
		<bndbox>
			<xmin>263</xmin>
			<xmax>495</xmax>
			<ymin>210</ymin>
			<ymax>415</ymax>
		</bndbox>
	</object>
</annotation>
