<annotation>
	<folder></folder>
	<filename>5142860483_jpg.rf.88a82b5b09b0283262f5d843709e9f5f.jpg</filename>
	<path>5142860483_jpg.rf.88a82b5b09b0283262f5d843709e9f5f.jpg</path>
	<source>
		<database>roboflow.ai</database>
	</source>
	<size>
		<width>640</width>
		<height>640</height>
		<depth>3</depth>
	</size>
	<segmented>0</segmented>
	<object>
		<name>qrcode</name>
		<pose>Unspecified</pose>
		<truncated>0</truncated>
		<difficult>0</difficult>
		<occluded>0</occluded>
		<bndbox>
			<xmin>184</xmin>
			<xmax>205</xmax>
			<ymin>172</ymin>
			<ymax>196</ymax>
		</bndbox>
	</object>
</annotation>
