<annotation>
	<folder></folder>
	<filename>6987A6D4-119C-4AA0-A7B6-FD9777B2C229_jpeg.rf.cd1a90ab0f0b7f3ea94bcc083de4bb37.jpg</filename>
	<path>6987A6D4-119C-4AA0-A7B6-FD9777B2C229_jpeg.rf.cd1a90ab0f0b7f3ea94bcc083de4bb37.jpg</path>
	<source>
		<database>roboflow.ai</database>
	</source>
	<size>
		<width>640</width>
		<height>640</height>
		<depth>3</depth>
	</size>
	<segmented>0</segmented>
	<object>
		<name>datamatrix</name>
		<pose>Unspecified</pose>
		<truncated>0</truncated>
		<difficult>0</difficult>
		<occluded>0</occluded>
		<bndbox>
			<xmin>439</xmin>
			<xmax>521</xmax>
			<ymin>364</ymin>
			<ymax>463</ymax>
		</bndbox>
	</object>
</annotation>
