<annotation>
	<folder></folder>
	<filename>Image261_jpg.rf.ea3189a50036ade81d42f9ee296039a0.jpg</filename>
	<path>Image261_jpg.rf.ea3189a50036ade81d42f9ee296039a0.jpg</path>
	<source>
		<database>roboflow.ai</database>
	</source>
	<size>
		<width>640</width>
		<height>640</height>
		<depth>3</depth>
	</size>
	<segmented>0</segmented>
	<object>
		<name>datamatrix</name>
		<pose>Unspecified</pose>
		<truncated>0</truncated>
		<difficult>0</difficult>
		<occluded>0</occluded>
		<bndbox>
			<xmin>215</xmin>
			<xmax>328</xmax>
			<ymin>368</ymin>
			<ymax>449</ymax>
		</bndbox>
	</object>
</annotation>
