<annotation>
	<folder></folder>
	<filename>IMG_20220601_165515_jpg.rf.96030ffdd913eed2a72116c5add5d23d.jpg</filename>
	<path>IMG_20220601_165515_jpg.rf.96030ffdd913eed2a72116c5add5d23d.jpg</path>
	<source>
		<database>roboflow.ai</database>
	</source>
	<size>
		<width>640</width>
		<height>640</height>
		<depth>3</depth>
	</size>
	<segmented>0</segmented>
	<object>
		<name>qrcode</name>
		<pose>Unspecified</pose>
		<truncated>0</truncated>
		<difficult>0</difficult>
		<occluded>0</occluded>
		<bndbox>
			<xmin>285</xmin>
			<xmax>364</xmax>
			<ymin>227</ymin>
			<ymax>316</ymax>
		</bndbox>
	</object>
</annotation>
