<annotation>
	<folder></folder>
	<filename>photo_2023-03-19_12-57-35_jpg.rf.b0d5f7e7f63959c4fe2eab4a79e0881d.jpg</filename>
	<path>photo_2023-03-19_12-57-35_jpg.rf.b0d5f7e7f63959c4fe2eab4a79e0881d.jpg</path>
	<source>
		<database>roboflow.ai</database>
	</source>
	<size>
		<width>640</width>
		<height>640</height>
		<depth>3</depth>
	</size>
	<segmented>0</segmented>
	<object>
		<name>datamatrix</name>
		<pose>Unspecified</pose>
		<truncated>0</truncated>
		<difficult>0</difficult>
		<occluded>0</occluded>
		<bndbox>
			<xmin>422</xmin>
			<xmax>457</xmax>
			<ymin>115</ymin>
			<ymax>159</ymax>
		</bndbox>
	</object>
	<object>
		<name>qrcode</name>
		<pose>Unspecified</pose>
		<truncated>0</truncated>
		<difficult>0</difficult>
		<occluded>0</occluded>
		<bndbox>
			<xmin>369</xmin>
			<xmax>454</xmax>
			<ymin>1</ymin>
			<ymax>63</ymax>
		</bndbox>
	</object>
	<object>
		<name>datamatrix</name>
		<pose>Unspecified</pose>
		<truncated>0</truncated>
		<difficult>0</difficult>
		<occluded>0</occluded>
		<bndbox>
			<xmin>344</xmin>
			<xmax>374</xmax>
			<ymin>379</ymin>
			<ymax>422</ymax>
		</bndbox>
	</object>
	<object>
		<name>datamatrix</name>
		<pose>Unspecified</pose>
		<truncated>0</truncated>
		<difficult>0</difficult>
		<occluded>0</occluded>
		<bndbox>
			<xmin>307</xmin>
			<xmax>332</xmax>
			<ymin>554</ymin>
			<ymax>596</ymax>
		</bndbox>
	</object>
</annotation>
